Metadata-Version: 2.1
Name: dpac-stravalib
Version: 0.10.2
Summary: Python library for interacting with Strava v3 REST API
Home-page: http://github.com/david-pacheco/stravalib
Author: David Pacheco
Author-email: davidpch@gmail.com
License: Apache
Platform: UNKNOWN
Classifier: Development Status :: 4 - Beta
Classifier: License :: OSI Approved :: Apache Software License
Classifier: Intended Audience :: Developers
Classifier: Operating System :: OS Independent
Classifier: Programming Language :: Python :: 2.7
Classifier: Programming Language :: Python :: 3
Classifier: Topic :: Software Development :: Libraries :: Python Modules
Requires-Dist: arrow
Requires-Dist: requests (<3.0dev,>=2.0)
Requires-Dist: units
Requires-Dist: pytz
Requires-Dist: six
